airbeeps/__init__.py
airbeeps/_version.py
airbeeps/cli.py
airbeeps/config.py
airbeeps/database.py
airbeeps/main.py
airbeeps/migrations.py
airbeeps/models.py
airbeeps/py.typed
airbeeps/seeder.py
airbeeps/agents/__init__.py
airbeeps/agents/descriptions.py
airbeeps/agents/executor.py
airbeeps/agents/models.py
airbeeps/agents/schemas.py
airbeeps/agents/service.py
airbeeps/agents/api/__init__.py
airbeeps/agents/api/v1/__init__.py
airbeeps/agents/api/v1/admin_router.py
airbeeps/agents/mcp/__init__.py
airbeeps/agents/mcp/client.py
airbeeps/agents/mcp/registry.py
airbeeps/agents/mcp/tools_adapter.py
airbeeps/agents/tools/__init__.py
airbeeps/agents/tools/base.py
airbeeps/agents/tools/knowledge_base.py
airbeeps/agents/tools/registry.py
airbeeps/ai_models/__init__.py
airbeeps/ai_models/catalog.py
airbeeps/ai_models/catalog.yaml
airbeeps/ai_models/client_factory.py
airbeeps/ai_models/hf_assets.py
airbeeps/ai_models/models.py
airbeeps/ai_models/api/__init__.py
airbeeps/ai_models/api/v1/__init__.py
airbeeps/ai_models/api/v1/admin_router.py
airbeeps/ai_models/api/v1/schemas.py
airbeeps/ai_models/api/v1/user_router.py
airbeeps/alembic/README
airbeeps/alembic/env.py
airbeeps/alembic/script.py.mako
airbeeps/alembic/versions/.gitkeep
airbeeps/alembic/versions/2026_01_01_1340-7a3c6f95150d_initial.py
airbeeps/assistants/__init__.py
airbeeps/assistants/models.py
airbeeps/assistants/api/__init__.py
airbeeps/assistants/api/v1/admin_router.py
airbeeps/assistants/api/v1/schemas.py
airbeeps/assistants/api/v1/user_router.py
airbeeps/auth/__init__.py
airbeeps/auth/auth_helpers.py
airbeeps/auth/dependencies.py
airbeeps/auth/fastapi_users.py
airbeeps/auth/manager.py
airbeeps/auth/oauth_models.py
airbeeps/auth/oauth_schemas.py
airbeeps/auth/oauth_service.py
airbeeps/auth/oauth_utils.py
airbeeps/auth/refresh_token_models.py
airbeeps/auth/refresh_token_service.py
airbeeps/auth/api/__init__.py
airbeeps/auth/api/v1/__init__.py
airbeeps/auth/api/v1/oauth_admin_router.py
airbeeps-0.1.5.dist-info/METADATA
airbeeps-0.1.5.dist-info/WHEEL
airbeeps-0.1.5.dist-info/entry_points.txt
airbeeps-0.1.5.dist-info/licenses/LICENSE
airbeeps-0.1.5.dist-info/RECORD
