Metadata-Version: 2.4
Name: airbeeps
Version: 0.1.5
Summary: Airbeeps - Local-first, self-hosted AI assistant for chat and RAG
Project-URL: Homepage, https://github.com/airbeeps/airbeeps
Project-URL: Repository, https://github.com/airbeeps/airbeeps
Project-URL: Documentation, https://github.com/airbeeps/airbeeps/tree/main/docs
Project-URL: Bug Tracker, https://github.com/airbeeps/airbeeps/issues
Project-URL: Changelog, https://github.com/airbeeps/airbeeps/blob/main/CHANGELOG.md
Author-email: Sreejith <hello@airbeeps.com>
License: MIT License
License-File: LICENSE
Keywords: ai,assistant,chat,fastapi,llm,rag
Classifier: Development Status :: 3 - Alpha
Classifier: Framework :: FastAPI
Classifier: Intended Audience :: Developers
Classifier: License :: OSI Approved :: MIT License
Classifier: Operating System :: OS Independent
Classifier: Programming Language :: Python :: 3
Classifier: Programming Language :: Python :: 3.13
Classifier: Topic :: Scientific/Engineering :: Artificial Intelligence
Requires-Python: <3.14,>=3.13
Requires-Dist: aioboto3>=15.1.0
Requires-Dist: aiomysql>=0.2.0
Requires-Dist: aiosqlite>=0.21.0
Requires-Dist: alembic>=1.16.5
Requires-Dist: asyncpg>=0.30.0
Requires-Dist: authlib>=1.6.4
Requires-Dist: boto3>=1.35.0
Requires-Dist: chromadb>=0.5.4
Requires-Dist: cryptography>=45.0.7
Requires-Dist: dashscope>=1.24.5
Requires-Dist: defusedxml>=0.7.1
Requires-Dist: fastapi-mail>=1.5.0
Requires-Dist: fastapi-pagination>=0.14.1
Requires-Dist: fastapi-users[sqlalchemy]>=14.0.1
Requires-Dist: fastapi[standard]>=0.116.1
Requires-Dist: filetype>=1.2.0
Requires-Dist: httpx>=0.28.1
Requires-Dist: itsdangerous>=2.2.0
Requires-Dist: langchain-chroma>=1.0.0
Requires-Dist: langchain-community>=0.4.1
Requires-Dist: langchain-huggingface>=0.1.0
Requires-Dist: langchain-text-splitters>=1.0.0
Requires-Dist: litellm>=1.80.10
Requires-Dist: magic-filter>=0.0.8
Requires-Dist: markitdown[docx,pdf,pptx,xls,xlsx]>=0.1.3
Requires-Dist: mcp>=1.18.0
Requires-Dist: pillow>=10.4.0
Requires-Dist: platformdirs>=4.0.0
Requires-Dist: pydantic-settings>=2.10.1
Requires-Dist: pymupdf>=1.24.0
Requires-Dist: python-multipart>=0.0.12
Requires-Dist: pyyaml>=6.0.2
Requires-Dist: rich>=13.0.0
Requires-Dist: sentence-transformers>=3.0.1
Requires-Dist: slowapi>=0.1.9
Requires-Dist: sqladmin>=0.21.0
Requires-Dist: sqlalchemy-utils>=0.42.0
Requires-Dist: sqlalchemy[asyncio]>=2.0.43
Requires-Dist: starlette-babel>=1.0.3
Requires-Dist: tiktoken>=0.11.0
Requires-Dist: typer>=0.12.5
